ndl_aspect/__init__.py
ndl_aspect-0.0.6.dist-info/LICENSE.txt
ndl_aspect-0.0.6.dist-info/METADATA
ndl_aspect-0.0.6.dist-info/WHEEL
ndl_aspect-0.0.6.dist-info/top_level.txt
ndl_aspect-0.0.6.dist-info/RECORD
