Metadata-Version: 2.1
Name: ndl_aspect
Version: 0.0.6
Summary: A package for training NDL models to predict aspect in Polish verbs
Home-page: https://github.com/pypa/sampleproject
Download-URL: https://github.com/ooominds/Polish-Aspect/archive/refs/tags/v_01.tar.gz
Author: Irene Testini
License: MIT
Keywords: NDL,NLP,Polish,Aspect
Classifier: License :: OSI Approved :: MIT License
Classifier: Programming Language :: Python :: 3
Classifier: License :: OSI Approved :: MIT License
Classifier: Operating System :: OS Independent
License-File: LICENSE.txt
Requires-Dist: numpy
Requires-Dist: pandas
Requires-Dist: pyndl
Requires-Dist: scikit-learn
Requires-Dist: keras
Requires-Dist: xarray
Requires-Dist: matplotlib
Requires-Dist: nltk
